nbdevminimum/__init__.py
nbdevminimum/_nbdev.py
nbdevminimum/convert.py
nbdevminimum/core.py
nbdevminimum-0.1.1.dist-info/LICENSE
nbdevminimum-0.1.1.dist-info/METADATA
nbdevminimum-0.1.1.dist-info/WHEEL
nbdevminimum-0.1.1.dist-info/entry_points.txt
nbdevminimum-0.1.1.dist-info/top_level.txt
nbdevminimum-0.1.1.dist-info/RECORD
