Metadata-Version: 2.1
Name: nbdevminimum
Version: 0.1.1
Summary: Minimal export of notebooks nbdev style for one-off projects that don't need to be a full library
Home-page: https://github.com/Isaac-Flath/nbdevminimum/tree/{branch}/
Author: Isaac Flath
Author-email: isaac.flath@gmail.com
License: Apache Software License 2.0
Keywords: nbdev jupyter
Platform: UNKNOWN
Classifier: Development Status :: 3 - Alpha
Classifier: Intended Audience :: Developers
Classifier: Natural Language :: English
Classifier: Programming Language :: Python :: 3.6
Classifier: Programming Language :: Python :: 3.7
Classifier: Programming Language :: Python :: 3.8
Classifier: License :: OSI Approved :: Apache Software License
Requires-Python: >=3.6
